{
    "$schema": "https://opendataschema.frama.io/catalog/schema-catalog.json",
    "version": 1,
    "schemas": [
        {
            "name": "etalab/schema-irve-statique",
            "title": "IRVE statique",
            "description": "Sp\u00e9cification du fichier d'\u00e9change relatif aux donn\u00e9es concernant la localisation g\u00e9ographique et les caract\u00e9ristiques techniques des stations et des points de recharge pour v\u00e9hicules \u00e9lectriques",
            "schema_url": "https://schema.data.gouv.fr/schemas/etalab/schema-irve-statique/latest/schema-statique.json",
            "schema_type": "tableschema",
            "contact": "contact@transport.beta.gouv.fr",
            "examples": [
                {
                    "title": "Exemple de fichier IRVE valide",
                    "path": "https://raw.githubusercontent.com/etalab/schema-irve/v2.3.0/statique/exemple-valide-statique.csv"
                }
            ],
            "labels": [
                "Socle Commun des Donn\u00e9es Locales",
                "transport.data.gouv.fr"
            ],
            "consolidation_dataset_id": "5448d3e0c751df01f85d0572",
            "versions": [
                {
                    "version_name": "2.2.0",
                    "schema_url": "https://schema.data.gouv.fr/schemas/etalab/schema-irve-statique/2.2.0/schema-statique.json"
                },
                {
                    "version_name": "2.2.1",
                    "schema_url": "https://schema.data.gouv.fr/schemas/etalab/schema-irve-statique/2.2.1/schema-statique.json"
                },
                {
                    "version_name": "2.3.0",
                    "schema_url": "https://schema.data.gouv.fr/schemas/etalab/schema-irve-statique/2.3.0/schema-statique.json"
                },
                {
                    "version_name": "2.3.1",
                    "schema_url": "https://schema.data.gouv.fr/schemas/etalab/schema-irve-statique/2.3.1/schema-statique.json"
                }
            ],
            "external_doc": "https://doc.transport.data.gouv.fr/producteurs/infrastructures-de-recharge-de-vehicules-electriques-irve",
            "external_tool": null,
            "homepage": "https://github.com/etalab/schema-irve.git",
            "datapackage_title": "Infrastructures de recharges pour v\u00e9hicules \u00e9lectriques (IRVE)",
            "datapackage_name": "etalab/schema-irve",
            "datapackage_description": "data package contenant 2 sch\u00e9mas : IRVE statique et IRVE dynamique"
        },
        {
            "name": "etalab/schema-irve-dynamique",
            "title": "IRVE dynamique",
            "description": "Sp\u00e9cification du fichier d'\u00e9change relatif aux donn\u00e9es concernant la localisation g\u00e9ographique et les caract\u00e9ristiques techniques des stations et des points de recharge pour v\u00e9hicules \u00e9lectriques",
            "schema_url": "https://schema.data.gouv.fr/schemas/etalab/schema-irve-dynamique/latest/schema-dynamique.json",
            "schema_type": "tableschema",
            "contact": "contact@transport.beta.gouv.fr",
            "examples": [
                {
                    "title": "Exemple de fichier IRVE valide",
                    "path": "https://raw.githubusercontent.com/etalab/schema-irve/v2.3.0/dynamique/exemple-valide-dynamique.csv"
                }
            ],
            "labels": [
                "Socle Commun des Donn\u00e9es Locales",
                "transport.data.gouv.fr"
            ],
            "consolidation_dataset_id": "5448d3e0c751df01f85d0572",
            "versions": [
                {
                    "version_name": "2.2.0",
                    "schema_url": "https://schema.data.gouv.fr/schemas/etalab/schema-irve-dynamique/2.2.0/schema-dynamique.json"
                },
                {
                    "version_name": "2.2.1",
                    "schema_url": "https://schema.data.gouv.fr/schemas/etalab/schema-irve-dynamique/2.2.1/schema-dynamique.json"
                },
                {
                    "version_name": "2.3.0",
                    "schema_url": "https://schema.data.gouv.fr/schemas/etalab/schema-irve-dynamique/2.3.0/schema-dynamique.json"
                },
                {
                    "version_name": "2.3.1",
                    "schema_url": "https://schema.data.gouv.fr/schemas/etalab/schema-irve-dynamique/2.3.1/schema-dynamique.json"
                }
            ],
            "external_doc": "https://doc.transport.data.gouv.fr/producteurs/infrastructures-de-recharge-de-vehicules-electriques-irve",
            "external_tool": null,
            "homepage": "https://github.com/etalab/schema-irve.git",
            "datapackage_title": "Infrastructures de recharges pour v\u00e9hicules \u00e9lectriques (IRVE)",
            "datapackage_name": "etalab/schema-irve",
            "datapackage_description": "data package contenant 2 sch\u00e9mas : IRVE statique et IRVE dynamique"
        },
        {
            "name": "etalab/schema-decp-dpa",
            "title": "Sp\u00e9cification du fichier de d\u00e9claration de profil d'acheteur",
            "description": "Sp\u00e9cification du fichier de d\u00e9claration de profil d'acheteur",
            "schema_url": "https://schema.data.gouv.fr/schemas/etalab/schema-decp-dpa/latest/schema.json",
            "schema_type": "tableschema",
            "contact": "schema@data.gouv.fr",
            "examples": [],
            "labels": [],
            "consolidation_dataset_id": null,
            "versions": [
                {
                    "version_name": "1.0.0",
                    "schema_url": "https://schema.data.gouv.fr/schemas/etalab/schema-decp-dpa/1.0.0/schema.json"
                }
            ],
            "external_doc": null,
            "external_tool": null,
            "homepage": "https://github.com/etalab/schema-decp-dpa.git"
        },
        {
            "name": "scdl/catalogue",
            "title": "Catalogue simplifi\u00e9",
            "description": "Sp\u00e9cification du mod\u00e8le de donn\u00e9es relatif au catalogue des jeux de donn\u00e9es publi\u00e9s en open data par une collectivit\u00e9",
            "schema_url": "https://schema.data.gouv.fr/schemas/scdl/catalogue/latest/schema.json",
            "schema_type": "tableschema",
            "contact": "scdl@opendatafrance.email",
            "examples": [],
            "labels": [
                "Socle Commun des Donn\u00e9es Locales"
            ],
            "consolidation_dataset_id": null,
            "versions": [
                {
                    "version_name": "0.1.1",
                    "schema_url": "https://schema.data.gouv.fr/schemas/scdl/catalogue/0.1.1/schema.json"
                },
                {
                    "version_name": "0.1.2",
                    "schema_url": "https://schema.data.gouv.fr/schemas/scdl/catalogue/0.1.2/schema.json"
                },
                {
                    "version_name": "0.1.3",
                    "schema_url": "https://schema.data.gouv.fr/schemas/scdl/catalogue/0.1.3/schema.json"
                }
            ],
            "external_doc": null,
            "external_tool": null,
            "homepage": "https://gitlab.com/opendatafrance/scdl/catalogue.git"
        },
        {
            "name": "scdl/deliberations",
            "title": "D\u00e9lib\u00e9rations",
            "description": "Sp\u00e9cification du mod\u00e8le de donn\u00e9es relatif aux d\u00e9lib\u00e9rations adopt\u00e9es par une collectivit\u00e9 locale",
            "schema_url": "https://schema.data.gouv.fr/schemas/scdl/deliberations/latest/schema.json",
            "schema_type": "tableschema",
            "contact": "scdl@opendatafrance.email",
            "examples": [
                {
                    "title": "Exemple de fichier d\u00e9lib\u00e9rations valide",
                    "path": "https://gitlab.com/opendatafrance/scdl/deliberations/raw/v2.1.5/examples/Deliberations_ok.csv"
                },
                {
                    "title": "Exemple de fichier d\u00e9lib\u00e9rations invalide",
                    "path": "https://gitlab.com/opendatafrance/scdl/deliberations/raw/v2.1.5/examples/Deliberations_coll_siret_ko.csv"
                }
            ],
            "labels": [
                "Socle Commun des Donn\u00e9es Locales"
            ],
            "consolidation_dataset_id": null,
            "versions": [
                {
                    "version_name": "1.1.0",
                    "schema_url": "https://schema.data.gouv.fr/schemas/scdl/deliberations/1.1.0/schema.json"
                },
                {
                    "version_name": "2.0.0",
                    "schema_url": "https://schema.data.gouv.fr/schemas/scdl/deliberations/2.0.0/schema.json"
                },
                {
                    "version_name": "2.1.0",
                    "schema_url": "https://schema.data.gouv.fr/schemas/scdl/deliberations/2.1.0/schema.json"
                },
                {
                    "version_name": "2.1.1",
                    "schema_url": "https://schema.data.gouv.fr/schemas/scdl/deliberations/2.1.1/schema.json"
                },
                {
                    "version_name": "2.1.2",
                    "schema_url": "https://schema.data.gouv.fr/schemas/scdl/deliberations/2.1.2/schema.json"
                },
                {
                    "version_name": "2.1.3",
                    "schema_url": "https://schema.data.gouv.fr/schemas/scdl/deliberations/2.1.3/schema.json"
                },
                {
                    "version_name": "2.1.4",
                    "schema_url": "https://schema.data.gouv.fr/schemas/scdl/deliberations/2.1.4/schema.json"
                },
                {
                    "version_name": "2.1.5",
                    "schema_url": "https://schema.data.gouv.fr/schemas/scdl/deliberations/2.1.5/schema.json"
                }
            ],
            "external_doc": null,
            "external_tool": null,
            "homepage": "https://gitlab.com/opendatafrance/scdl/deliberations.git"
        },
        {
            "name": "scdl/equipements",
            "title": "\u00c9quipements",
            "description": "Sp\u00e9cification du mod\u00e8le de donn\u00e9es relatif aux \u00e9quipements collectifs publics d'une collectivit\u00e9",
            "schema_url": "https://schema.data.gouv.fr/schemas/scdl/equipements/latest/schema.json",
            "schema_type": "tableschema",
            "contact": "scdl@opendatafrance.email",
            "examples": [],
            "labels": [
                "Socle Commun des Donn\u00e9es Locales"
            ],
            "consolidation_dataset_id": null,
            "versions": [
                {
                    "version_name": "0.1.0",
                    "schema_url": "https://schema.data.gouv.fr/schemas/scdl/equipements/0.1.0/schema.json"
                },
                {
                    "version_name": "0.1.1",
                    "schema_url": "https://schema.data.gouv.fr/schemas/scdl/equipements/0.1.1/schema.json"
                },
                {
                    "version_name": "0.1.2",
                    "schema_url": "https://schema.data.gouv.fr/schemas/scdl/equipements/0.1.2/schema.json"
                },
                {
                    "version_name": "0.1.3",
                    "schema_url": "https://schema.data.gouv.fr/schemas/scdl/equipements/0.1.3/schema.json"
                },
                {
                    "version_name": "0.1.4",
                    "schema_url": "https://schema.data.gouv.fr/schemas/scdl/equipements/0.1.4/schema.json"
                },
                {
                    "version_name": "0.1.5",
                    "schema_url": "https://schema.data.gouv.fr/schemas/scdl/equipements/0.1.5/schema.json"
                }
            ],
            "external_doc": null,
            "external_tool": null,
            "homepage": "https://gitlab.com/opendatafrance/scdl/equipements.git"
        },
        {
            "name": "scdl/subventions",
            "title": "Subventions",
            "description": "Sp\u00e9cification du mod\u00e8le de donn\u00e9es relatif aux subventions attribu\u00e9es par une collectivit\u00e9",
            "schema_url": "https://schema.data.gouv.fr/schemas/scdl/subventions/latest/schema.json",
            "schema_type": "tableschema",
            "contact": "scdl@opendatafrance.email",
            "examples": [
                {
                    "title": "Exemple de fichier subventions valide",
                    "path": "https://gitlab.com/opendatafrance/scdl/subventions/raw/v2.1.1/exemples/exemple_valide.csv"
                },
                {
                    "title": "Exemple de fichier subventions invalide (erreurs cellules)",
                    "path": "https://gitlab.com/opendatafrance/scdl/subventions/raw/v2.1.1/exemples/exemple_invalide_erreurs_cellules.csv"
                },
                {
                    "title": "Exemple de fichier subventions invalide (erreurs colonnes)",
                    "path": "https://gitlab.com/opendatafrance/scdl/subventions/raw/v2.1.1/exemples/exemple_invalide_erreurs_colonnes.csv"
                }
            ],
            "labels": [
                "Socle Commun des Donn\u00e9es Locales"
            ],
            "consolidation_dataset_id": null,
            "versions": [
                {
                    "version_name": "1.1.0",
                    "schema_url": "https://schema.data.gouv.fr/schemas/scdl/subventions/1.1.0/schema.json"
                },
                {
                    "version_name": "2.0.0",
                    "schema_url": "https://schema.data.gouv.fr/schemas/scdl/subventions/2.0.0/schema.json"
                },
                {
                    "version_name": "2.0.1",
                    "schema_url": "https://schema.data.gouv.fr/schemas/scdl/subventions/2.0.1/schema.json"
                },
                {
                    "version_name": "2.0.2",
                    "schema_url": "https://schema.data.gouv.fr/schemas/scdl/subventions/2.0.2/schema.json"
                },
                {
                    "version_name": "2.1.0",
                    "schema_url": "https://schema.data.gouv.fr/schemas/scdl/subventions/2.1.0/schema.json"
                },
                {
                    "version_name": "2.1.1",
                    "schema_url": "https://schema.data.gouv.fr/schemas/scdl/subventions/2.1.1/schema.json"
                }
            ],
            "external_doc": null,
            "external_tool": null,
            "homepage": "https://gitlab.com/opendatafrance/scdl/subventions.git"
        },
        {
            "name": "etalab/schema-lieux-covoiturage",
            "title": "Lieux de covoiturage",
            "description": "Sp\u00e9cification des lieux permettant le covoiturage",
            "schema_url": "https://schema.data.gouv.fr/schemas/etalab/schema-lieux-covoiturage/latest/schema.json",
            "schema_type": "tableschema",
            "contact": "contact@transport.beta.gouv.fr",
            "examples": [
                {
                    "title": "Ressource valide",
                    "name": "exemple-valide",
                    "path": "https://github.com/etalab/schema-lieux-covoiturage/raw/v0.3.0/exemple-valide.csv"
                },
                {
                    "title": "Ressource invalide",
                    "name": "exemple-invalide",
                    "path": "https://github.com/etalab/schema-lieux-covoiturage/raw/v0.3.0/exemple-invalide.csv"
                }
            ],
            "labels": [
                "transport.data.gouv.fr"
            ],
            "consolidation_dataset_id": "5d6eaffc8b4c417cdc452ac3",
            "versions": [
                {
                    "version_name": "0.0.1",
                    "schema_url": "https://schema.data.gouv.fr/schemas/etalab/schema-lieux-covoiturage/0.0.1/schema.json"
                },
                {
                    "version_name": "0.1.0",
                    "schema_url": "https://schema.data.gouv.fr/schemas/etalab/schema-lieux-covoiturage/0.1.0/schema.json"
                },
                {
                    "version_name": "0.1.1",
                    "schema_url": "https://schema.data.gouv.fr/schemas/etalab/schema-lieux-covoiturage/0.1.1/schema.json"
                },
                {
                    "version_name": "0.1.2",
                    "schema_url": "https://schema.data.gouv.fr/schemas/etalab/schema-lieux-covoiturage/0.1.2/schema.json"
                },
                {
                    "version_name": "0.2.0",
                    "schema_url": "https://schema.data.gouv.fr/schemas/etalab/schema-lieux-covoiturage/0.2.0/schema.json"
                },
                {
                    "version_name": "0.2.1",
                    "schema_url": "https://schema.data.gouv.fr/schemas/etalab/schema-lieux-covoiturage/0.2.1/schema.json"
                },
                {
                    "version_name": "0.2.2",
                    "schema_url": "https://schema.data.gouv.fr/schemas/etalab/schema-lieux-covoiturage/0.2.2/schema.json"
                },
                {
                    "version_name": "0.2.3",
                    "schema_url": "https://schema.data.gouv.fr/schemas/etalab/schema-lieux-covoiturage/0.2.3/schema.json"
                },
                {
                    "version_name": "0.2.4",
                    "schema_url": "https://schema.data.gouv.fr/schemas/etalab/schema-lieux-covoiturage/0.2.4/schema.json"
                },
                {
                    "version_name": "0.2.5",
                    "schema_url": "https://schema.data.gouv.fr/schemas/etalab/schema-lieux-covoiturage/0.2.5/schema.json"
                },
                {
                    "version_name": "0.2.6",
                    "schema_url": "https://schema.data.gouv.fr/schemas/etalab/schema-lieux-covoiturage/0.2.6/schema.json"
                },
                {
                    "version_name": "0.2.7",
                    "schema_url": "https://schema.data.gouv.fr/schemas/etalab/schema-lieux-covoiturage/0.2.7/schema.json"
                },
                {
                    "version_name": "0.2.8",
                    "schema_url": "https://schema.data.gouv.fr/schemas/etalab/schema-lieux-covoiturage/0.2.8/schema.json"
                },
                {
                    "version_name": "0.3.0",
                    "schema_url": "https://schema.data.gouv.fr/schemas/etalab/schema-lieux-covoiturage/0.3.0/schema.json"
                }
            ],
            "external_doc": null,
            "external_tool": "https://contribuer.transport.data.gouv.fr",
            "homepage": "https://github.com/etalab/schema-lieux-covoiturage.git"
        },
        {
            "name": "etalab/schema-stationnement",
            "title": "Lieux de stationnement",
            "description": "Sp\u00e9cification des lieux permettant le stationnement en parc",
            "schema_url": "https://schema.data.gouv.fr/schemas/etalab/schema-stationnement/latest/schema.json",
            "schema_type": "tableschema",
            "contact": "contact@transport.beta.gouv.fr",
            "examples": [
                {
                    "title": "Ressource valide (CSV)",
                    "name": "exemple-valide-csv",
                    "path": "https://github.com/etalab/schema-stationnement/raw/v0.1.5/exemple-valide.csv"
                },
                {
                    "title": "Ressource valide (XLSX)",
                    "name": "exemple-valide-xlsx",
                    "path": "https://github.com/etalab/schema-stationnement/raw/v0.1.5/exemple-valide.xlsx"
                },
                {
                    "title": "Ressource invalide",
                    "name": "exemple-invalide",
                    "path": "https://github.com/etalab/schema-stationnement/raw/v0.1.5/exemple-invalide.csv"
                }
            ],
            "labels": [
                "transport.data.gouv.fr"
            ],
            "consolidation_dataset_id": "5ea1add4a5a7dac3af82310a",
            "versions": [
                {
                    "version_name": "0.1.4",
                    "schema_url": "https://schema.data.gouv.fr/schemas/etalab/schema-stationnement/0.1.4/schema.json"
                },
                {
                    "version_name": "0.1.5",
                    "schema_url": "https://schema.data.gouv.fr/schemas/etalab/schema-stationnement/0.1.5/schema.json"
                }
            ],
            "external_doc": null,
            "external_tool": null,
            "homepage": "https://github.com/etalab/schema-stationnement.git"
        },
        {
            "name": "scdl/budget",
            "title": "Budget des collectivit\u00e9s et \u00e9tablissements publics locaux",
            "description": "Les donn\u00e9es essentielles du budget permettent de d\u00e9crire le contenu des \u00e9tapes budg\u00e9taires des collectivit\u00e9s locales et des \u00e9tablissements publics. Il permet de pr\u00e9ciser les cat\u00e9gories de montants financiers ainsi que le d\u00e9coupage de ces sommes en fonction du type de pr\u00e9sentation utilis\u00e9 (par nature ou par fonction). Ce sch\u00e9ma d\u00e9crit le d\u00e9tail de chaque champ et le cas \u00e9ch\u00e9ant les r\u00e8gles de validit\u00e9 associ\u00e9es.",
            "schema_url": "https://schema.data.gouv.fr/schemas/scdl/budget/latest/schema.json",
            "schema_type": "tableschema",
            "contact": "scdl@opendatafrance.email",
            "examples": [
                {
                    "title": "Exemple de fichier budget valide",
                    "path": "https://gitlab.com/opendatafrance/scdl/budget/raw/v0.8.3/examples/budget_valide.csv"
                }
            ],
            "labels": [
                "Socle Commun des Donn\u00e9es Locales"
            ],
            "consolidation_dataset_id": null,
            "versions": [
                {
                    "version_name": "0.8.1",
                    "schema_url": "https://schema.data.gouv.fr/schemas/scdl/budget/0.8.1/schema.json"
                },
                {
                    "version_name": "0.8.2",
                    "schema_url": "https://schema.data.gouv.fr/schemas/scdl/budget/0.8.2/schema.json"
                },
                {
                    "version_name": "0.8.3",
                    "schema_url": "https://schema.data.gouv.fr/schemas/scdl/budget/0.8.3/schema.json"
                }
            ],
            "external_doc": null,
            "external_tool": null,
            "homepage": "https://gitlab.com/opendatafrance/scdl/budget.git"
        },
        {
            "name": "atlasante/schema-dae",
            "title": "DAE",
            "description": "Sp\u00e9cification du mod\u00e8le de donn\u00e9es relatif aux DAE",
            "schema_url": "https://schema.data.gouv.fr/schemas/atlasante/schema-dae/latest/schema.json",
            "schema_type": "tableschema",
            "contact": "contact@geodae.sante.gouv.fr",
            "examples": [
                {
                    "title": "Exemple de fichier DAE avec des donn\u00e9es invalides",
                    "path": "https://gitlab.com/arsante/atlasante/schema-dae/raw/1.0.7/exemple_invalide.csv"
                },
                {
                    "title": "Exemple de fichier DAE avec une structure invalide",
                    "path": "https://gitlab.com/arsante/atlasante/schema-dae/raw/1.0.7/exemple_invalide_structure.csv"
                },
                {
                    "title": "Exemple de fichier DAE toutes les donn\u00e9es invalides",
                    "path": "https://gitlab.com/arsante/atlasante/schema-dae/raw/1.0.7/exemple_invalide_complet.csv"
                },
                {
                    "title": "Exemple de fichier DAE valide",
                    "path": "https://gitlab.com/arsante/atlasante/schema-dae/raw/1.0.7/exemple_valide.csv"
                }
            ],
            "labels": [
                "Socle Commun des Donn\u00e9es Locales"
            ],
            "consolidation_dataset_id": null,
            "versions": [
                {
                    "version_name": "1.0.2",
                    "schema_url": "https://schema.data.gouv.fr/schemas/atlasante/schema-dae/1.0.2/schema.json"
                },
                {
                    "version_name": "1.0.3",
                    "schema_url": "https://schema.data.gouv.fr/schemas/atlasante/schema-dae/1.0.3/schema.json"
                },
                {
                    "version_name": "1.0.4",
                    "schema_url": "https://schema.data.gouv.fr/schemas/atlasante/schema-dae/1.0.4/schema.json"
                },
                {
                    "version_name": "1.0.5",
                    "schema_url": "https://schema.data.gouv.fr/schemas/atlasante/schema-dae/1.0.5/schema.json"
                },
                {
                    "version_name": "1.0.6",
                    "schema_url": "https://schema.data.gouv.fr/schemas/atlasante/schema-dae/1.0.6/schema.json"
                },
                {
                    "version_name": "1.0.7",
                    "schema_url": "https://schema.data.gouv.fr/schemas/atlasante/schema-dae/1.0.7/schema.json"
                }
            ],
            "external_doc": null,
            "external_tool": null,
            "homepage": "https://gitlab.com/arsante/atlasante/schema-dae.git"
        },
        {
            "name": "scdl/prenoms",
            "title": "Pr\u00e9noms des nouveaux-n\u00e9s",
            "description": "Sp\u00e9cification du mod\u00e8le de donn\u00e9es relatif aux pr\u00e9noms des nouveaux-n\u00e9s d\u00e9clar\u00e9s \u00e0 l\u2019\u00e9tat-civil",
            "schema_url": "https://schema.data.gouv.fr/schemas/scdl/prenoms/latest/schema.json",
            "schema_type": "tableschema",
            "contact": "scdl@opendatafrance.email",
            "examples": [
                {
                    "title": "Exemple de fichier des pr\u00e9noms valide",
                    "path": "https://gitlab.com/opendatafrance/scdl/prenoms/raw/v1.1.6/examples/prenoms-nouveaux-nes_exemple-valide.csv"
                },
                {
                    "title": "Exemple de fichier des pr\u00e9noms invalide",
                    "path": "https://gitlab.com/opendatafrance/scdl/prenoms/raw/v1.1.6/examples/prenoms-nouveaux-nes_exemple-invalide.csv"
                }
            ],
            "labels": [
                "Socle Commun des Donn\u00e9es Locales"
            ],
            "consolidation_dataset_id": null,
            "versions": [
                {
                    "version_name": "1.1.5",
                    "schema_url": "https://schema.data.gouv.fr/schemas/scdl/prenoms/1.1.5/schema.json"
                },
                {
                    "version_name": "1.1.6",
                    "schema_url": "https://schema.data.gouv.fr/schemas/scdl/prenoms/1.1.6/schema.json"
                }
            ],
            "external_doc": null,
            "external_tool": null,
            "homepage": "https://gitlab.com/opendatafrance/scdl/prenoms.git"
        },
        {
            "name": "NaturalSolutions/schema-arbre",
            "title": "Arbres urbains",
            "description": "Sp\u00e9cification des attributs li\u00e9s aux arbres urbains dans le cadre d'un inventaire du patrimoine arbor\u00e9 par les collectivit\u00e9s.",
            "schema_url": "https://schema.data.gouv.fr/schemas/NaturalSolutions/schema-arbre/latest/schema.json",
            "schema_type": "tableschema",
            "contact": "contact@natural-solutions.eu",
            "examples": [
                {
                    "title": "Fichier valide (CSV)",
                    "name": "exemple-valide-csv",
                    "path": "https://raw.githubusercontent.com/NaturalSolutions/schema-arbre/v0.2.2/exemple-valide.csv"
                },
                {
                    "title": "Ressource valide (XLSX)",
                    "name": "exemple-valide-xlsx",
                    "path": "https://raw.githubusercontent.com/NaturalSolutions/schema-arbre/v0.2.2/exemple-valide.xlsx"
                }
            ],
            "labels": [],
            "consolidation_dataset_id": null,
            "versions": [
                {
                    "version_name": "0.1.0",
                    "schema_url": "https://schema.data.gouv.fr/schemas/NaturalSolutions/schema-arbre/0.1.0/schema.json"
                },
                {
                    "version_name": "0.2.0",
                    "schema_url": "https://schema.data.gouv.fr/schemas/NaturalSolutions/schema-arbre/0.2.0/schema.json"
                },
                {
                    "version_name": "0.2.1",
                    "schema_url": "https://schema.data.gouv.fr/schemas/NaturalSolutions/schema-arbre/0.2.1/schema.json"
                },
                {
                    "version_name": "0.2.2",
                    "schema_url": "https://schema.data.gouv.fr/schemas/NaturalSolutions/schema-arbre/0.2.2/schema.json"
                },
                {
                    "version_name": "0.3.0",
                    "schema_url": "https://schema.data.gouv.fr/schemas/NaturalSolutions/schema-arbre/0.3.0/schema.json"
                },
                {
                    "version_name": "0.3.1",
                    "schema_url": "https://schema.data.gouv.fr/schemas/NaturalSolutions/schema-arbre/0.3.1/schema.json"
                }
            ],
            "external_doc": null,
            "external_tool": null,
            "homepage": "https://github.com/NaturalSolutions/schema-arbre.git"
        },
        {
            "name": "etalab/schema-stationnement-cyclable",
            "title": "Stationnement cyclable",
            "description": "Sp\u00e9cification du fichier d\u00e9crivant les emplacements de stationnement cycable.",
            "schema_url": "https://schema.data.gouv.fr/schemas/etalab/schema-stationnement-cyclable/latest/schema.json",
            "schema_type": "tableschema",
            "contact": "contact@transport.beta.gouv.fr",
            "examples": [
                {
                    "title": "Ressource valide (CSV)",
                    "name": "exemple-valide-csv",
                    "path": "https://github.com/etalab/schema-stationnement-cyclable/raw/v1.1.1/exemple-valide.csv"
                },
                {
                    "title": "Ressource invalide",
                    "name": "exemple-invalide",
                    "path": "https://github.com/etalab/schema-stationnement-cyclable/raw/v1.1.1/exemple-invalide.csv"
                }
            ],
            "labels": [
                "transport.data.gouv.fr"
            ],
            "consolidation_dataset_id": null,
            "versions": [
                {
                    "version_name": "0.1.0",
                    "schema_url": "https://schema.data.gouv.fr/schemas/etalab/schema-stationnement-cyclable/0.1.0/schema.json"
                },
                {
                    "version_name": "0.2.0",
                    "schema_url": "https://schema.data.gouv.fr/schemas/etalab/schema-stationnement-cyclable/0.2.0/schema.json"
                },
                {
                    "version_name": "0.2.1",
                    "schema_url": "https://schema.data.gouv.fr/schemas/etalab/schema-stationnement-cyclable/0.2.1/schema.json"
                },
                {
                    "version_name": "1.0.0",
                    "schema_url": "https://schema.data.gouv.fr/schemas/etalab/schema-stationnement-cyclable/1.0.0/schema.json"
                },
                {
                    "version_name": "1.1.0",
                    "schema_url": "https://schema.data.gouv.fr/schemas/etalab/schema-stationnement-cyclable/1.1.0/schema.json"
                },
                {
                    "version_name": "1.1.1",
                    "schema_url": "https://schema.data.gouv.fr/schemas/etalab/schema-stationnement-cyclable/1.1.1/schema.json"
                }
            ],
            "external_doc": "https://doc.transport.data.gouv.fr/producteurs/documentation-sur-le-stationnement-cyclable",
            "external_tool": null,
            "homepage": "https://github.com/etalab/schema-stationnement-cyclable"
        },
        {
            "name": "LaMednum/standard-mediation-num",
            "title": "Lieux de m\u00e9diation num\u00e9rique",
            "description": "Sp\u00e9cification du standard national des lieux de m\u00e9diation num\u00e9rique",
            "schema_url": "https://schema.data.gouv.fr/schemas/LaMednum/standard-mediation-num/latest/schema.json",
            "schema_type": "tableschema",
            "contact": "contact@lamednum.coop",
            "examples": [
                {
                    "title": "Fichier valide (CSV)",
                    "name": "exemple-valide-csv",
                    "path": "https://raw.githubusercontent.com/LaMednum/standard-mediation-num/main/exemple-valide.csv"
                }
            ],
            "labels": [],
            "consolidation_dataset_id": null,
            "versions": [
                {
                    "version_name": "0.1.0",
                    "schema_url": "https://schema.data.gouv.fr/schemas/LaMednum/standard-mediation-num/0.1.0/schema.json"
                },
                {
                    "version_name": "0.1.1",
                    "schema_url": "https://schema.data.gouv.fr/schemas/LaMednum/standard-mediation-num/0.1.1/schema.json"
                },
                {
                    "version_name": "1.0.0",
                    "schema_url": "https://schema.data.gouv.fr/schemas/LaMednum/standard-mediation-num/1.0.0/schema.json"
                },
                {
                    "version_name": "1.0.1",
                    "schema_url": "https://schema.data.gouv.fr/schemas/LaMednum/standard-mediation-num/1.0.1/schema.json"
                }
            ],
            "external_doc": null,
            "external_tool": null,
            "homepage": "https://github.com/LaMednum/standard-mediation-num.git"
        },
        {
            "name": "etalab/schema-hautes-remunerations",
            "title": "Hautes r\u00e9mun\u00e9rations dans la fonction publique",
            "description": "Sp\u00e9cification du fichier de d\u00e9claration des dix r\u00e9mun\u00e9rations les plus \u00e9lev\u00e9es des agents publiques",
            "schema_url": "https://schema.data.gouv.fr/schemas/etalab/schema-hautes-remunerations/latest/schema.json",
            "schema_type": "tableschema",
            "contact": "schema@data.gouv.fr",
            "examples": [],
            "labels": [],
            "consolidation_dataset_id": null,
            "versions": [
                {
                    "version_name": "0.1.0",
                    "schema_url": "https://schema.data.gouv.fr/schemas/etalab/schema-hautes-remunerations/0.1.0/schema.json"
                }
            ],
            "external_doc": null,
            "external_tool": null,
            "homepage": "https://github.com/etalab/schema-hautes-remunerations"
        },
        {
            "name": "scdl/menus-collectifs",
            "title": "Menus de la restauration collective",
            "description": "Sch\u00e9ma permettant de d\u00e9crire les menus des repas propos\u00e9s par les collectivit\u00e9s locales, les \u00e9tablissements publics et priv\u00e9s. Il permet de pr\u00e9ciser les modalit\u00e9s de distribution et le contenu des menus propos\u00e9s (les plats). Le choix a \u00e9t\u00e9 fait de d\u00e9tailler chaque plat sur une ligne. Pour d\u00e9crire un menu il faut donc r\u00e9p\u00e9ter certaines informations plusieurs fois (voir exemple).",
            "schema_url": "https://schema.data.gouv.fr/schemas/scdl/menus-collectifs/latest/schema.json",
            "schema_type": "tableschema",
            "contact": "scdl@opendatafrance.email",
            "examples": [
                {
                    "title": "Exemple de fichier de menus valide en csv",
                    "path": "https://gitlab.com/opendatafrance/scdl/menus-collectifs/-/raw/v1.2.3/examples/menus-collectifs_valide.csv"
                },
                {
                    "title": "Exemple de fichier de menus valide en Office Open XML",
                    "path": "https://gitlab.com/opendatafrance/scdl/menus-collectifs/-/raw/v1.2.3/examples/menus-collectifs_valide.xlsx"
                }
            ],
            "labels": [
                "Socle Commun des Donn\u00e9es Locales"
            ],
            "consolidation_dataset_id": null,
            "versions": [
                {
                    "version_name": "0.1.0",
                    "schema_url": "https://schema.data.gouv.fr/schemas/scdl/menus-collectifs/0.1.0/schema.json"
                },
                {
                    "version_name": "0.2.0",
                    "schema_url": "https://schema.data.gouv.fr/schemas/scdl/menus-collectifs/0.2.0/schema.json"
                },
                {
                    "version_name": "0.4.0",
                    "schema_url": "https://schema.data.gouv.fr/schemas/scdl/menus-collectifs/0.4.0/schema.json"
                },
                {
                    "version_name": "0.5.0",
                    "schema_url": "https://schema.data.gouv.fr/schemas/scdl/menus-collectifs/0.5.0/schema.json"
                },
                {
                    "version_name": "0.6.0",
                    "schema_url": "https://schema.data.gouv.fr/schemas/scdl/menus-collectifs/0.6.0/schema.json"
                },
                {
                    "version_name": "0.7.0",
                    "schema_url": "https://schema.data.gouv.fr/schemas/scdl/menus-collectifs/0.7.0/schema.json"
                },
                {
                    "version_name": "0.9.0",
                    "schema_url": "https://schema.data.gouv.fr/schemas/scdl/menus-collectifs/0.9.0/schema.json"
                },
                {
                    "version_name": "1.2.0",
                    "schema_url": "https://schema.data.gouv.fr/schemas/scdl/menus-collectifs/1.2.0/schema.json"
                },
                {
                    "version_name": "1.2.1",
                    "schema_url": "https://schema.data.gouv.fr/schemas/scdl/menus-collectifs/1.2.1/schema.json"
                },
                {
                    "version_name": "1.2.2",
                    "schema_url": "https://schema.data.gouv.fr/schemas/scdl/menus-collectifs/1.2.2/schema.json"
                },
                {
                    "version_name": "1.2.3",
                    "schema_url": "https://schema.data.gouv.fr/schemas/scdl/menus-collectifs/1.2.3/schema.json"
                }
            ],
            "external_doc": null,
            "external_tool": null,
            "homepage": "https://gitlab.com/opendatafrance/scdl/menus-collectifs.git"
        },
        {
            "name": "scdl/plats-menus-collectifs",
            "title": "Composition des plats des menus de la restauration collective",
            "description": "Description des plats propos\u00e9s par des collectivit\u00e9s locales, des \u00e9tablissements publics et des entreprises dans le cadre de l'offre de restauration collective. Il permet de pr\u00e9ciser les modalit\u00e9s de fabrication des plats et de d\u00e9tailler les produits qui les composent. Ce sch\u00e9ma d\u00e9crit le d\u00e9tail de chaque champ et le cas \u00e9ch\u00e9ant les r\u00e8gles de validit\u00e9 associ\u00e9es. Il peut \u00eatre utilis\u00e9 ind\u00e9pendamment ou en compl\u00e9ment du le sch\u00e9ma sur les menus collectifs qui d\u00e9crit la composition en plats.",
            "schema_url": "https://schema.data.gouv.fr/schemas/scdl/plats-menus-collectifs/latest/schema.json",
            "schema_type": "tableschema",
            "contact": "scdl@opendatafrance.email",
            "examples": [
                {
                    "title": "Exemple de fichier de menus valide en csv",
                    "path": "https://gitlab.com/opendatafrance/scdl/plats-menus-collectifs/raw/v0.7.2/examples/plats-collectifs_valide.csv"
                },
                {
                    "title": "Exemple de fichier de menus valide en OOXML",
                    "path": "https://gitlab.com/opendatafrance/scdl/plats-menus-collectifs/raw/v0.7.2/examples/plats-collectifs_valide.xlsx"
                }
            ],
            "labels": [
                "Socle Commun des Donn\u00e9es Locales"
            ],
            "consolidation_dataset_id": null,
            "versions": [
                {
                    "version_name": "0.2.0",
                    "schema_url": "https://schema.data.gouv.fr/schemas/scdl/plats-menus-collectifs/0.2.0/schema.json"
                },
                {
                    "version_name": "0.3.0",
                    "schema_url": "https://schema.data.gouv.fr/schemas/scdl/plats-menus-collectifs/0.3.0/schema.json"
                },
                {
                    "version_name": "0.4.0",
                    "schema_url": "https://schema.data.gouv.fr/schemas/scdl/plats-menus-collectifs/0.4.0/schema.json"
                },
                {
                    "version_name": "0.7.0",
                    "schema_url": "https://schema.data.gouv.fr/schemas/scdl/plats-menus-collectifs/0.7.0/schema.json"
                },
                {
                    "version_name": "0.7.1",
                    "schema_url": "https://schema.data.gouv.fr/schemas/scdl/plats-menus-collectifs/0.7.1/schema.json"
                },
                {
                    "version_name": "0.7.2",
                    "schema_url": "https://schema.data.gouv.fr/schemas/scdl/plats-menus-collectifs/0.7.2/schema.json"
                }
            ],
            "external_doc": null,
            "external_tool": null,
            "homepage": "https://gitlab.com/opendatafrance/scdl/plats-menus-collectifs.git"
        },
        {
            "name": "MTES-MCT/acceslibre-schema",
            "title": "Sch\u00e9ma des donn\u00e9es d'accessibilit\u00e9 des ERPs",
            "description": "Sp\u00e9cification du fichier d'\u00e9change relatif aux donn\u00e9es d'accessibilit\u00e9 des \u00c9tablissements Recevant du Public (ERP).",
            "schema_url": "https://schema.data.gouv.fr/schemas/MTES-MCT/acceslibre-schema/latest/schema.json",
            "schema_type": "tableschema",
            "contact": "acceslibre@beta.gouv.fr",
            "examples": [
                {
                    "title": "Fichier valide (CSV)",
                    "name": "exemple-valide-csv",
                    "path": "https://github.com/MTES-MCT/acceslibre-schema/raw/v0.0.10/exemple-valide.csv"
                },
                {
                    "title": "Sch\u00e9ma au format XLS",
                    "name": "schema_format_xls",
                    "path": "https://github.com/MTES-MCT/acceslibre-schema/blob/v0.0.10/schema_format_excel.xls"
                }
            ],
            "labels": [],
            "consolidation_dataset_id": null,
            "versions": [
                {
                    "version_name": "0.0.1",
                    "schema_url": "https://schema.data.gouv.fr/schemas/MTES-MCT/acceslibre-schema/0.0.1/schema.json"
                },
                {
                    "version_name": "0.0.2",
                    "schema_url": "https://schema.data.gouv.fr/schemas/MTES-MCT/acceslibre-schema/0.0.2/schema.json"
                },
                {
                    "version_name": "0.0.3",
                    "schema_url": "https://schema.data.gouv.fr/schemas/MTES-MCT/acceslibre-schema/0.0.3/schema.json"
                },
                {
                    "version_name": "0.0.4",
                    "schema_url": "https://schema.data.gouv.fr/schemas/MTES-MCT/acceslibre-schema/0.0.4/schema.json"
                },
                {
                    "version_name": "0.0.5",
                    "schema_url": "https://schema.data.gouv.fr/schemas/MTES-MCT/acceslibre-schema/0.0.5/schema.json"
                },
                {
                    "version_name": "0.0.6",
                    "schema_url": "https://schema.data.gouv.fr/schemas/MTES-MCT/acceslibre-schema/0.0.6/schema.json"
                },
                {
                    "version_name": "0.0.7",
                    "schema_url": "https://schema.data.gouv.fr/schemas/MTES-MCT/acceslibre-schema/0.0.7/schema.json"
                },
                {
                    "version_name": "0.0.8",
                    "schema_url": "https://schema.data.gouv.fr/schemas/MTES-MCT/acceslibre-schema/0.0.8/schema.json"
                },
                {
                    "version_name": "0.0.9",
                    "schema_url": "https://schema.data.gouv.fr/schemas/MTES-MCT/acceslibre-schema/0.0.9/schema.json"
                },
                {
                    "version_name": "0.0.10",
                    "schema_url": "https://schema.data.gouv.fr/schemas/MTES-MCT/acceslibre-schema/0.0.10/schema.json"
                },
                {
                    "version_name": "0.0.13",
                    "schema_url": "https://schema.data.gouv.fr/schemas/MTES-MCT/acceslibre-schema/0.0.13/schema.json"
                },
                {
                    "version_name": "0.0.14",
                    "schema_url": "https://schema.data.gouv.fr/schemas/MTES-MCT/acceslibre-schema/0.0.14/schema.json"
                },
                {
                    "version_name": "0.0.15",
                    "schema_url": "https://schema.data.gouv.fr/schemas/MTES-MCT/acceslibre-schema/0.0.15/schema.json"
                }
            ],
            "external_doc": null,
            "external_tool": null,
            "homepage": "https://github.com/MTES-MCT/acceslibre-schema.git"
        },
        {
            "name": "etalab/schema-sdirve",
            "title": "Sch\u00e9ma directeur des infrastructures de recharge pour v\u00e9hicules \u00e9lectriques et hybrides rechargeables",
            "description": "Sp\u00e9cification du fichier d'\u00e9change relatif aux sch\u00e9ma directeur des infrastructures de recharge pour v\u00e9hicules \u00e9lectriques et hybrides rechargeables.",
            "schema_url": "https://schema.data.gouv.fr/schemas/etalab/schema-sdirve/latest/schema.json",
            "schema_type": "tableschema",
            "contact": "schema@data.gouv.fr",
            "examples": [
                {
                    "title": "Fichier valide (CSV)",
                    "name": "exemple-valide-csv",
                    "path": "https://github.com/etalab/schema-sdirve/raw/v0.1.0/exemple-valide.csv"
                }
            ],
            "labels": [],
            "consolidation_dataset_id": null,
            "versions": [
                {
                    "version_name": "0.1.0",
                    "schema_url": "https://schema.data.gouv.fr/schemas/etalab/schema-sdirve/0.1.0/schema.json"
                }
            ],
            "external_doc": null,
            "external_tool": null,
            "homepage": "https://github.com/etalab/schema-sdirve.git"
        },
        {
            "name": "Archivistes75/registre_entrees",
            "title": "Registre d'entr\u00e9e d'archives",
            "description": "Sp\u00e9cification du standard national des registres d'entr\u00e9e d'archives",
            "schema_url": "https://schema.data.gouv.fr/schemas/Archivistes75/registre_entrees/latest/schema.json",
            "schema_type": "tableschema",
            "contact": "hello@datactivist.coop",
            "examples": [],
            "labels": [],
            "consolidation_dataset_id": null,
            "versions": [
                {
                    "version_name": "0.2.0",
                    "schema_url": "https://schema.data.gouv.fr/schemas/Archivistes75/registre_entrees/0.2.0/schema.json"
                },
                {
                    "version_name": "0.3.1",
                    "schema_url": "https://schema.data.gouv.fr/schemas/Archivistes75/registre_entrees/0.3.1/schema.json"
                }
            ],
            "external_doc": null,
            "external_tool": null,
            "homepage": "https://github.com/Archivistes75/registre_entrees.git"
        },
        {
            "name": "CEREMA/schema-arrete-circulation-marchandises",
            "title": "Arr\u00eat\u00e9s permanents de circulation pour le transport de marchandises",
            "description": "Sp\u00e9cification du fichier d'\u00e9change relatif aux arr\u00eat\u00e9s permanents de circulation pour le transport de marchandises g\u00e9r\u00e9s par les collectivit\u00e9s.",
            "schema_url": "https://schema.data.gouv.fr/schemas/CEREMA/schema-arrete-circulation-marchandises/latest/schema.json",
            "schema_type": "tableschema",
            "contact": "data-med@cerema.fr",
            "examples": [
                {
                    "title": "Fichier valide",
                    "name": "exemple-valide-csv",
                    "path": "https://raw.githubusercontent.com/CEREMA/schema-arrete-circulation-marchandises/v0.9.2/exemple-valide.csv"
                },
                {
                    "title": "Fichier valide pour la commune de Carros (CSV)",
                    "name": "carros-csv",
                    "path": "https://raw.githubusercontent.com/CEREMA/schema-arrete-circulation-marchandises/v0.9.2/exemples/carros.csv"
                },
                {
                    "title": "Fichier valide pour la commune de Gignac-La-Nerthe (CSV)",
                    "name": "gignac-csv",
                    "path": "https://raw.githubusercontent.com/CEREMA/schema-arrete-circulation-marchandises/v0.9.2/exemples/gignac.csv"
                },
                {
                    "title": "Fichier valide pour la commune du Rove (CSV)",
                    "name": "le-rove-csv",
                    "path": "https://raw.githubusercontent.com/CEREMA/schema-arrete-circulation-marchandises/v0.9.2/exemples/le-rove.csv"
                },
                {
                    "title": "Fichier valide pour la commune de St-Victoret (CSV)",
                    "name": "st-victoret-csv",
                    "path": "https://raw.githubusercontent.com/CEREMA/schema-arrete-circulation-marchandises/v0.9.2/exemples/st-victoret.csv"
                },
                {
                    "title": "Fichier valide pour la commune de Sept\u00e8mes-Les-Vallons (CSV)",
                    "name": "septemes-les-vallons-csv",
                    "path": "https://raw.githubusercontent.com/CEREMA/schema-arrete-circulation-marchandises/v0.9.2/exemples/septemes-les-vallons.csv"
                },
                {
                    "title": "Fichier valide pour la commune de Vence (CSV)",
                    "name": "vence-csv",
                    "path": "https://raw.githubusercontent.com/CEREMA/schema-arrete-circulation-marchandises/v0.9.2/exemples/vence.csv"
                }
            ],
            "labels": [],
            "consolidation_dataset_id": null,
            "versions": [
                {
                    "version_name": "0.3.0",
                    "schema_url": "https://schema.data.gouv.fr/schemas/CEREMA/schema-arrete-circulation-marchandises/0.3.0/schema.json"
                },
                {
                    "version_name": "0.4.0",
                    "schema_url": "https://schema.data.gouv.fr/schemas/CEREMA/schema-arrete-circulation-marchandises/0.4.0/schema.json"
                },
                {
                    "version_name": "0.4.1",
                    "schema_url": "https://schema.data.gouv.fr/schemas/CEREMA/schema-arrete-circulation-marchandises/0.4.1/schema.json"
                },
                {
                    "version_name": "0.5.0",
                    "schema_url": "https://schema.data.gouv.fr/schemas/CEREMA/schema-arrete-circulation-marchandises/0.5.0/schema.json"
                },
                {
                    "version_name": "0.6.0",
                    "schema_url": "https://schema.data.gouv.fr/schemas/CEREMA/schema-arrete-circulation-marchandises/0.6.0/schema.json"
                },
                {
                    "version_name": "0.6.1",
                    "schema_url": "https://schema.data.gouv.fr/schemas/CEREMA/schema-arrete-circulation-marchandises/0.6.1/schema.json"
                },
                {
                    "version_name": "0.6.2",
                    "schema_url": "https://schema.data.gouv.fr/schemas/CEREMA/schema-arrete-circulation-marchandises/0.6.2/schema.json"
                },
                {
                    "version_name": "0.6.3",
                    "schema_url": "https://schema.data.gouv.fr/schemas/CEREMA/schema-arrete-circulation-marchandises/0.6.3/schema.json"
                },
                {
                    "version_name": "0.7.0",
                    "schema_url": "https://schema.data.gouv.fr/schemas/CEREMA/schema-arrete-circulation-marchandises/0.7.0/schema.json"
                },
                {
                    "version_name": "0.7.1",
                    "schema_url": "https://schema.data.gouv.fr/schemas/CEREMA/schema-arrete-circulation-marchandises/0.7.1/schema.json"
                },
                {
                    "version_name": "0.7.2",
                    "schema_url": "https://schema.data.gouv.fr/schemas/CEREMA/schema-arrete-circulation-marchandises/0.7.2/schema.json"
                },
                {
                    "version_name": "0.8.0",
                    "schema_url": "https://schema.data.gouv.fr/schemas/CEREMA/schema-arrete-circulation-marchandises/0.8.0/schema.json"
                },
                {
                    "version_name": "0.9.0",
                    "schema_url": "https://schema.data.gouv.fr/schemas/CEREMA/schema-arrete-circulation-marchandises/0.9.0/schema.json"
                },
                {
                    "version_name": "0.9.1",
                    "schema_url": "https://schema.data.gouv.fr/schemas/CEREMA/schema-arrete-circulation-marchandises/0.9.1/schema.json"
                },
                {
                    "version_name": "0.9.2",
                    "schema_url": "https://schema.data.gouv.fr/schemas/CEREMA/schema-arrete-circulation-marchandises/0.9.2/schema.json"
                }
            ],
            "external_doc": null,
            "external_tool": null,
            "homepage": "https://github.com/CEREMA/schema-arrete-circulation-marchandises.git"
        },
        {
            "name": "openmaraude/schema-stationstaxi",
            "title": "Stations de taxi",
            "description": "Sp\u00e9cification des stations de taxi \u00e0 usage public",
            "schema_url": "https://schema.data.gouv.fr/schemas/openmaraude/schema-stationstaxi/latest/schema.json",
            "schema_type": "tableschema",
            "contact": "tech@le.taxi",
            "examples": [
                {
                    "title": "Fichier valide (CSV)",
                    "name": "exemple-valide-csv",
                    "path": "https://github.com/openmaraude/schema-stationstaxi/raw/v0.1.2/exemple-valide.csv"
                }
            ],
            "labels": [],
            "consolidation_dataset_id": null,
            "versions": [
                {
                    "version_name": "0.1.0",
                    "schema_url": "https://schema.data.gouv.fr/schemas/openmaraude/schema-stationstaxi/0.1.0/schema.json"
                },
                {
                    "version_name": "0.1.1",
                    "schema_url": "https://schema.data.gouv.fr/schemas/openmaraude/schema-stationstaxi/0.1.1/schema.json"
                },
                {
                    "version_name": "0.1.2",
                    "schema_url": "https://schema.data.gouv.fr/schemas/openmaraude/schema-stationstaxi/0.1.2/schema.json"
                }
            ],
            "external_doc": null,
            "external_tool": null,
            "homepage": "https://github.com/openmaraude/schema-stationstaxi.git"
        },
        {
            "name": "etalab/schema-vehicules-faibles-emissions-renouvellement-parc",
            "title": "Part des v\u00e9hicules \u00e0 faibles \u00e9missions dans le renouvellement d'un parc",
            "description": "Sp\u00e9cification des donn\u00e9es fixant les termes et modalit\u00e9s de publication du pourcentage de v\u00e9hicules \u00e0 faibles et \u00e0 tr\u00e8s faibles \u00e9missions parmi les v\u00e9hicules int\u00e9gr\u00e9s dans un renouvellement de parc",
            "schema_url": "https://schema.data.gouv.fr/schemas/etalab/schema-vehicules-faibles-emissions-renouvellement-parc/latest/schema.json",
            "schema_type": "tableschema",
            "contact": "schema@data.gouv.fr",
            "examples": [
                {
                    "title": "Fichier valide (CSV)",
                    "name": "exemple-valide-csv",
                    "path": "https://github.com/etalab/schema-flotte-publique-vehicule/raw/v0.1.3/exemple-valide.csv"
                }
            ],
            "labels": [],
            "consolidation_dataset_id": null,
            "versions": [
                {
                    "version_name": "0.1.0",
                    "schema_url": "https://schema.data.gouv.fr/schemas/etalab/schema-vehicules-faibles-emissions-renouvellement-parc/0.1.0/schema.json"
                },
                {
                    "version_name": "0.1.1",
                    "schema_url": "https://schema.data.gouv.fr/schemas/etalab/schema-vehicules-faibles-emissions-renouvellement-parc/0.1.1/schema.json"
                },
                {
                    "version_name": "0.1.2",
                    "schema_url": "https://schema.data.gouv.fr/schemas/etalab/schema-vehicules-faibles-emissions-renouvellement-parc/0.1.2/schema.json"
                },
                {
                    "version_name": "0.1.3",
                    "schema_url": "https://schema.data.gouv.fr/schemas/etalab/schema-vehicules-faibles-emissions-renouvellement-parc/0.1.3/schema.json"
                }
            ],
            "external_doc": null,
            "external_tool": null,
            "homepage": "https://github.com/etalab/schema-vehicules-faibles-emissions-renouvellement-parc.git"
        },
        {
            "name": "datakode/schema-pei",
            "title": "Point d'Eau Incendie (PEI)",
            "description": "Sp\u00e9cification du mod\u00e8le de donn\u00e9es relatif aux PEI",
            "schema_url": "https://schema.data.gouv.fr/schemas/datakode/schema-pei/latest/schema.json",
            "schema_type": "tableschema",
            "contact": "portier@datakode.fr",
            "examples": [
                {
                    "title": "Imp\u00e9mentations",
                    "path": "https://docs.google.com/spreadsheets/d/1UBlX52Of20q4HnAFTyxrfX75vZrUtXDxwXP6j6_kUp4/edit#gid=0"
                }
            ],
            "labels": [],
            "consolidation_dataset_id": null,
            "versions": [
                {
                    "version_name": "1.0.0",
                    "schema_url": "https://schema.data.gouv.fr/schemas/datakode/schema-pei/1.0.0/schema.json"
                },
                {
                    "version_name": "1.0.1",
                    "schema_url": "https://schema.data.gouv.fr/schemas/datakode/schema-pei/1.0.1/schema.json"
                }
            ],
            "external_doc": null,
            "external_tool": null,
            "homepage": "https://gitlab.com/datakode/schema-pei.git"
        },
        {
            "name": "etalab/schema-passage-a-niveau",
            "title": "Sch\u00e9ma pour les passages \u00e0 niveau",
            "description": "Sp\u00e9cification du fichier d\u00e9crivant les emplacements de passages \u00e0 niveau.",
            "schema_url": "https://schema.data.gouv.fr/schemas/etalab/schema-passage-a-niveau/latest/schema.json",
            "schema_type": "tableschema",
            "contact": "contact@transport.beta.gouv.fr",
            "examples": [
                {
                    "title": "Fichier valide (CSV)",
                    "name": "exemple-valide-csv",
                    "path": "https://github.com/etalab/schema-passage-a-niveau/raw/v0.1.0/exemple-valide.csv"
                }
            ],
            "labels": [
                "transport.data.gouv.fr"
            ],
            "consolidation_dataset_id": null,
            "versions": [
                {
                    "version_name": "0.1.0",
                    "schema_url": "https://schema.data.gouv.fr/schemas/etalab/schema-passage-a-niveau/0.1.0/schema.json"
                }
            ],
            "external_doc": null,
            "external_tool": null,
            "homepage": "https://github.com/etalab/schema-passage-a-niveau"
        },
        {
            "name": "etalab/schema-comptage-mobilites-site",
            "title": "Comptage des mobilit\u00e9s (Site)",
            "description": "Sp\u00e9cification du fichier d'\u00e9change relatif aux comptages des mobilit\u00e9s.",
            "schema_url": "https://schema.data.gouv.fr/schemas/etalab/schema-comptage-mobilites-site/latest/schema.json",
            "schema_type": "tableschema",
            "contact": "contact@transport.beta.gouv.fr",
            "examples": [
                {
                    "title": "Fichier valide (CSV)",
                    "name": "exemple-valide-csv",
                    "path": "https://raw.githubusercontent.com/etalab/schema-comptage-mobilites/v0.2.4/site/exemple-valide.csv"
                },
                {
                    "title": "Deuxi\u00e8me fichier valide (CSV)",
                    "name": "exemple-valide-eco-compteur.csv",
                    "path": "https://raw.githubusercontent.com/etalab/schema-comptage-mobilites/v0.2.4/site/exemple-valide-eco-compteur.csv"
                }
            ],
            "labels": [
                "transport.data.gouv.fr"
            ],
            "consolidation_dataset_id": null,
            "versions": [
                {
                    "version_name": "0.2.3",
                    "schema_url": "https://schema.data.gouv.fr/schemas/etalab/schema-comptage-mobilites-site/0.2.3/schema.json"
                },
                {
                    "version_name": "0.2.4",
                    "schema_url": "https://schema.data.gouv.fr/schemas/etalab/schema-comptage-mobilites-site/0.2.4/schema.json"
                }
            ],
            "external_doc": "https://doc.transport.data.gouv.fr/producteurs/comptage-des-mobilites",
            "external_tool": null,
            "homepage": "https://github.com/etalab/schema-comptage-mobilites",
            "datapackage_title": "Comptage des mobilit\u00e9s",
            "datapackage_name": "etalab/schema-comptage-mobilites",
            "datapackage_description": "Data package contenant 3 sch\u00e9mas : site, channel, measure"
        },
        {
            "name": "etalab/schema-comptage-mobilites-channel",
            "title": "Comptage des mobilit\u00e9s (Channel)",
            "description": "Sp\u00e9cification du fichier d'\u00e9change relatif aux comptages des mobilit\u00e9s.",
            "schema_url": "https://schema.data.gouv.fr/schemas/etalab/schema-comptage-mobilites-channel/latest/schema.json",
            "schema_type": "tableschema",
            "contact": "contact@transport.beta.gouv.fr",
            "examples": [
                {
                    "title": "Fichier valide (CSV)",
                    "name": "exemple-valide-csv",
                    "path": "https://raw.githubusercontent.com/etalab/schema-comptage-mobilites/v0.2.4/channel/exemple-valide.csv"
                },
                {
                    "title": "Deuxi\u00e8me fichier valide (CSV)",
                    "name": "exemple-valide-eco-compteur.csv",
                    "path": "https://raw.githubusercontent.com/etalab/schema-comptage-mobilites/v0.2.4/channel/exemple-valide-eco-compteur.csv"
                }
            ],
            "labels": [
                "transport.data.gouv.fr"
            ],
            "consolidation_dataset_id": null,
            "versions": [
                {
                    "version_name": "0.2.3",
                    "schema_url": "https://schema.data.gouv.fr/schemas/etalab/schema-comptage-mobilites-channel/0.2.3/schema.json"
                },
                {
                    "version_name": "0.2.4",
                    "schema_url": "https://schema.data.gouv.fr/schemas/etalab/schema-comptage-mobilites-channel/0.2.4/schema.json"
                }
            ],
            "external_doc": "https://doc.transport.data.gouv.fr/producteurs/comptage-des-mobilites",
            "external_tool": null,
            "homepage": "https://github.com/etalab/schema-comptage-mobilites",
            "datapackage_title": "Comptage des mobilit\u00e9s",
            "datapackage_name": "etalab/schema-comptage-mobilites",
            "datapackage_description": "Data package contenant 3 sch\u00e9mas : site, channel, measure"
        },
        {
            "name": "etalab/schema-comptage-mobilites-measure",
            "title": "Comptage des mobilit\u00e9s (Measure)",
            "description": "Sp\u00e9cification du fichier d'\u00e9change relatif aux comptages des mobilit\u00e9s.",
            "schema_url": "https://schema.data.gouv.fr/schemas/etalab/schema-comptage-mobilites-measure/latest/schema.json",
            "schema_type": "tableschema",
            "contact": "contact@transport.beta.gouv.fr",
            "examples": [
                {
                    "title": "Fichier valide (CSV)",
                    "name": "exemple-valide-csv",
                    "path": "https://raw.githubusercontent.com/etalab/schema-comptage-mobilites/v0.2.4/measure/exemple-valide.csv"
                },
                {
                    "title": "Deuxi\u00e8me fichier valide (CSV)",
                    "name": "exemple-valide-eco-compteur.csv",
                    "path": "https://raw.githubusercontent.com/etalab/schema-comptage-mobilites/v0.2.4/measure/exemple-valide-eco-compteur.csv"
                }
            ],
            "labels": [
                "transport.data.gouv.fr"
            ],
            "consolidation_dataset_id": null,
            "versions": [
                {
                    "version_name": "0.2.3",
                    "schema_url": "https://schema.data.gouv.fr/schemas/etalab/schema-comptage-mobilites-measure/0.2.3/schema.json"
                },
                {
                    "version_name": "0.2.4",
                    "schema_url": "https://schema.data.gouv.fr/schemas/etalab/schema-comptage-mobilites-measure/0.2.4/schema.json"
                }
            ],
            "external_doc": "https://doc.transport.data.gouv.fr/producteurs/comptage-des-mobilites",
            "external_tool": null,
            "homepage": "https://github.com/etalab/schema-comptage-mobilites",
            "datapackage_title": "Comptage des mobilit\u00e9s",
            "datapackage_name": "etalab/schema-comptage-mobilites",
            "datapackage_description": "Data package contenant 3 sch\u00e9mas : site, channel, measure"
        },
        {
            "name": "etalab/schema-dispositif-aide",
            "title": "Dispositifs d'aides",
            "description": "Sp\u00e9cification du fichier d'\u00e9change relatif aux dispositifs d'aides.",
            "schema_url": "https://schema.data.gouv.fr/schemas/etalab/schema-dispositif-aide/latest/schema.json",
            "schema_type": "tableschema",
            "contact": "aides-territoires@beta.gouv.fr",
            "examples": [
                {
                    "title": "Fichier valide (CSV)",
                    "name": "exemple-valide-csv",
                    "path": "https://github.com/etalab/schema-dispositif-aide/raw/v0.0.1/exemple-valide.csv"
                }
            ],
            "labels": [],
            "consolidation_dataset_id": null,
            "versions": [
                {
                    "version_name": "0.0.1",
                    "schema_url": "https://schema.data.gouv.fr/schemas/etalab/schema-dispositif-aide/0.0.1/schema.json"
                },
                {
                    "version_name": "0.0.2",
                    "schema_url": "https://schema.data.gouv.fr/schemas/etalab/schema-dispositif-aide/0.0.2/schema.json"
                }
            ],
            "external_doc": null,
            "external_tool": null,
            "homepage": "https://github.com/etalab/schema-dispositif-aide.git"
        },
        {
            "name": "etalab/schema-vehicules-faibles-emissions-renouvellement-parc-synthese",
            "title": "Part des v\u00e9hicules \u00e0 faibles \u00e9missions dans le renouvellement des parcs d\u2019entreprises de location, location-vente, de cr\u00e9dit-bail de v\u00e9hicules, des plateformes de livraisons et des centrales de r\u00e9servation de taxi et VTC",
            "description": "Sp\u00e9cification du fichier d\u2019\u00e9change relatif aux parts de v\u00e9hicules \u00e0 faibles \u00e9missions dans les parcs de v\u00e9hicules des entreprises de location, location-vente et cr\u00e9dit-bail de v\u00e9hicules, des plateformes de livraison, des centrales de r\u00e9servation de taxi et de VTC. Certaines donn\u00e9es demand\u00e9es n\u00e9cessitent des champs qui doivent \u00eatre transmis aux services de l'administration comp\u00e9tents, mais dont la publication sur data.gouv.fr n'est pas obligatoire.",
            "schema_url": "https://schema.data.gouv.fr/schemas/etalab/schema-vehicules-faibles-emissions-renouvellement-parc-synthese/latest/schema.json",
            "schema_type": "tableschema",
            "contact": "schema@data.gouv.fr",
            "examples": [
                {
                    "title": "Fichier valide (CSV)",
                    "name": "exemple-valide-csv",
                    "path": "https://github.com/geoffreyaldebert/schema-vehicules-faibles-emissions-renouvellement-parc-synthese/raw/v0.0.2/exemple-valide.csv"
                }
            ],
            "labels": [],
            "consolidation_dataset_id": null,
            "versions": [
                {
                    "version_name": "0.0.1",
                    "schema_url": "https://schema.data.gouv.fr/schemas/etalab/schema-vehicules-faibles-emissions-renouvellement-parc-synthese/0.0.1/schema.json"
                },
                {
                    "version_name": "0.0.2",
                    "schema_url": "https://schema.data.gouv.fr/schemas/etalab/schema-vehicules-faibles-emissions-renouvellement-parc-synthese/0.0.2/schema.json"
                }
            ],
            "external_doc": null,
            "external_tool": null,
            "homepage": "https://github.com/etalab/schema-vehicules-faibles-emissions-renouvellement-parc-synthese.git"
        },
        {
            "name": "cnigfr/schema-friches",
            "title": "Standard CNIG Friches",
            "description": "Sp\u00e9cification du fichier d'\u00e9change conforme au standard CNIG Friches relatif aux friches urbanis\u00e9es. Une friche \"urbanis\u00e9e\" a connu une activit\u00e9 \u00e9conomique (industrielle, artisanale, logistique, commerciale, de loisir, tertiaire, agricole), un usage r\u00e9sidentiel ou un usage d'\u00e9quipement. La d\u00e9finition r\u00e8glementaire d\u00e9crit \"tout bien ou droit immobilier, b\u00e2ti ou non b\u00e2ti, inutilis\u00e9 et dont l'\u00e9tat, la configuration ou l'occupation totale ou partielle ne permet pas un r\u00e9emploi sans un am\u00e9nagement ou des travaux pr\u00e9alables\". En particulier, les friches dites \"agricoles\", au sens des espaces auparavant cultiv\u00e9s et qui se sont enfrich\u00e9s, ne sont pas prises en compte dans le cadre de ce standard, au contraire des b\u00e2tis agricoles d\u00e9saffect\u00e9s.",
            "schema_url": "https://schema.data.gouv.fr/schemas/cnigfr/schema-friches/latest/schema.json",
            "schema_type": "tableschema",
            "contact": "cnig@cnig.fr",
            "examples": [
                {
                    "title": "Fichier valide",
                    "name": "exemple-valide-csv",
                    "path": "https://github.com/cnigfr/schema-friches/raw/v1.0.5/fichier-valide.csv"
                }
            ],
            "labels": [
                "CNIG"
            ],
            "consolidation_dataset_id": null,
            "versions": [
                {
                    "version_name": "1.0.1",
                    "schema_url": "https://schema.data.gouv.fr/schemas/cnigfr/schema-friches/1.0.1/schema.json"
                },
                {
                    "version_name": "1.0.2",
                    "schema_url": "https://schema.data.gouv.fr/schemas/cnigfr/schema-friches/1.0.2/schema.json"
                },
                {
                    "version_name": "1.0.3",
                    "schema_url": "https://schema.data.gouv.fr/schemas/cnigfr/schema-friches/1.0.3/schema.json"
                },
                {
                    "version_name": "1.0.4",
                    "schema_url": "https://schema.data.gouv.fr/schemas/cnigfr/schema-friches/1.0.4/schema.json"
                },
                {
                    "version_name": "1.0.5",
                    "schema_url": "https://schema.data.gouv.fr/schemas/cnigfr/schema-friches/1.0.5/schema.json"
                }
            ],
            "external_doc": null,
            "external_tool": null,
            "homepage": "https://github.com/cnigfr/schema-friches.git"
        },
        {
            "name": "etalab/schema-indice-reparabilite",
            "title": "Indice de r\u00e9parabilit\u00e9",
            "description": "Sch\u00e9ma de donn\u00e9es pour l'indice de r\u00e9parabilit\u00e9",
            "schema_url": "https://schema.data.gouv.fr/schemas/etalab/schema-indice-reparabilite/latest/schema.json",
            "schema_type": "tableschema",
            "contact": "schema@data.gouv.fr",
            "examples": [
                {
                    "title": "Fichier valide (CSV)",
                    "name": "exemple-valide-csv",
                    "path": "https://github.com/etalab/schema-indice-reparabilite/blob/master/exemple-valide.csv"
                }
            ],
            "labels": [],
            "consolidation_dataset_id": null,
            "versions": [
                {
                    "version_name": "0.1.0",
                    "schema_url": "https://schema.data.gouv.fr/schemas/etalab/schema-indice-reparabilite/0.1.0/schema.json"
                },
                {
                    "version_name": "0.1.1",
                    "schema_url": "https://schema.data.gouv.fr/schemas/etalab/schema-indice-reparabilite/0.1.1/schema.json"
                },
                {
                    "version_name": "0.1.2",
                    "schema_url": "https://schema.data.gouv.fr/schemas/etalab/schema-indice-reparabilite/0.1.2/schema.json"
                }
            ],
            "external_doc": null,
            "external_tool": null,
            "homepage": "https://github.com/etalab/schema-indice-reparabilite.git"
        },
        {
            "name": "etalab/schema-impact-service-public-numerique",
            "title": "Impact d\u2019un service public num\u00e9rique",
            "description": "Sch\u00e9ma de donn\u00e9es pour les indicateurs d\u2019impact d\u2019un service public num\u00e9rique",
            "schema_url": "https://schema.data.gouv.fr/schemas/etalab/schema-impact-service-public-numerique/latest/schema.json",
            "schema_type": "tableschema",
            "contact": "schema@data.gouv.fr",
            "examples": [
                {
                    "title": "Fichier valide (CSV)",
                    "name": "exemple-valide-csv",
                    "path": "https://github.com/etalab/schema-impact-service-public-numerique/raw/v0.3.0/exemple-valide.csv"
                }
            ],
            "labels": [],
            "consolidation_dataset_id": null,
            "versions": [
                {
                    "version_name": "0.0.1",
                    "schema_url": "https://schema.data.gouv.fr/schemas/etalab/schema-impact-service-public-numerique/0.0.1/schema.json"
                },
                {
                    "version_name": "0.2.0",
                    "schema_url": "https://schema.data.gouv.fr/schemas/etalab/schema-impact-service-public-numerique/0.2.0/schema.json"
                },
                {
                    "version_name": "0.2.1",
                    "schema_url": "https://schema.data.gouv.fr/schemas/etalab/schema-impact-service-public-numerique/0.2.1/schema.json"
                },
                {
                    "version_name": "0.2.2",
                    "schema_url": "https://schema.data.gouv.fr/schemas/etalab/schema-impact-service-public-numerique/0.2.2/schema.json"
                },
                {
                    "version_name": "0.3.0",
                    "schema_url": "https://schema.data.gouv.fr/schemas/etalab/schema-impact-service-public-numerique/0.3.0/schema.json"
                }
            ],
            "external_doc": null,
            "external_tool": null,
            "homepage": "https://github.com/etalab/schema-impact-service-public-numerique"
        },
        {
            "name": "cnigfr/sites-economiques-pole-eco",
            "title": "Classe POLE-ECO du standard CNIG Sites Economiques",
            "description": "Sp\u00e9cification du fichier d'\u00e9change conforme au standard CNIG Sites Economiques pour la classe POLE-ECO : P\u00f4le \u00e9conomique",
            "schema_url": "https://schema.data.gouv.fr/schemas/cnigfr/sites-economiques-pole-eco/latest/schema.json",
            "schema_type": "tableschema",
            "contact": "cnig@cnig.fr",
            "examples": [
                {
                    "title": "Exemple valide",
                    "name": "exemple-valide-csv",
                    "path": "https://github.com/cnigfr/schema-sites-economiques/schema/pole-eco/raw/v1.0.0/exemple-valide.csv"
                }
            ],
            "labels": [
                "CNIG"
            ],
            "consolidation_dataset_id": null,
            "versions": [
                {
                    "version_name": "1.0.0",
                    "schema_url": "https://schema.data.gouv.fr/schemas/cnigfr/sites-economiques-pole-eco/1.0.0/schema.json"
                }
            ],
            "external_doc": null,
            "external_tool": null,
            "homepage": "https://github.com/cnigfr/schema-sites-economiques.git",
            "datapackage_title": "Site Economique",
            "datapackage_name": "cnigfr/schema-sites-economiques",
            "datapackage_description": "Data package contenant 4 sch\u00e9mas : pole-eco, site-eco, terrain-eco, etablissement"
        },
        {
            "name": "cnigfr/sites-economiques-site-eco",
            "title": "Classe SITE-ECO du standard CNIG Sites Economiques",
            "description": "Sp\u00e9cification du fichier d'\u00e9change conforme au standard CNIG Sites Economiques pour la classe SITE-ECO : Site \u00e9conomique",
            "schema_url": "https://schema.data.gouv.fr/schemas/cnigfr/sites-economiques-site-eco/latest/schema.json",
            "schema_type": "tableschema",
            "contact": "cnig@cnig.fr",
            "examples": [
                {
                    "title": "Exemple valide",
                    "name": "exemple-valide-csv",
                    "path": "https://github.com/cnigfr/schema-sites-economiques/schema/site-eco/raw/v1.0.0/exemple-valide.csv"
                }
            ],
            "labels": [
                "CNIG"
            ],
            "consolidation_dataset_id": null,
            "versions": [
                {
                    "version_name": "1.0.0",
                    "schema_url": "https://schema.data.gouv.fr/schemas/cnigfr/sites-economiques-site-eco/1.0.0/schema.json"
                }
            ],
            "external_doc": null,
            "external_tool": null,
            "homepage": "https://github.com/cnigfr/schema-sites-economiques.git",
            "datapackage_title": "Site Economique",
            "datapackage_name": "cnigfr/schema-sites-economiques",
            "datapackage_description": "Data package contenant 4 sch\u00e9mas : pole-eco, site-eco, terrain-eco, etablissement"
        },
        {
            "name": "cnigfr/sites-economiques-terrain-eco",
            "title": "Classe TERRAIN-ECO du standard CNIG Sites Economiques",
            "description": "Sp\u00e9cification du fichier d'\u00e9change conforme au standard CNIG Sites Economiques pour la classe TERRAIN-ECO : terrain \u00e9conomique",
            "schema_url": "https://schema.data.gouv.fr/schemas/cnigfr/sites-economiques-terrain-eco/latest/schema.json",
            "schema_type": "tableschema",
            "contact": "cnig@cnig.fr",
            "examples": [
                {
                    "title": "Exemple valide",
                    "name": "exemple-valide-csv",
                    "path": "https://github.com/cnigfr/schema-sites-economiques/schema/terrain-eco/raw/v1.0.0/exemple-valide.csv"
                }
            ],
            "labels": [
                "CNIG"
            ],
            "consolidation_dataset_id": null,
            "versions": [
                {
                    "version_name": "1.0.0",
                    "schema_url": "https://schema.data.gouv.fr/schemas/cnigfr/sites-economiques-terrain-eco/1.0.0/schema.json"
                }
            ],
            "external_doc": null,
            "external_tool": null,
            "homepage": "https://github.com/cnigfr/schema-sites-economiques.git",
            "datapackage_title": "Site Economique",
            "datapackage_name": "cnigfr/schema-sites-economiques",
            "datapackage_description": "Data package contenant 4 sch\u00e9mas : pole-eco, site-eco, terrain-eco, etablissement"
        },
        {
            "name": "cnigfr/sites-economiques-etablissement",
            "title": "Classe ETABLISSEMENT du standard CNIG Sites Economiques",
            "description": "Sp\u00e9cification du fichier d'\u00e9change conforme au standard CNIG Sites Economiques pour la classe ETABLISSEMENT : \u00e9tablissement \u00e9conomique",
            "schema_url": "https://schema.data.gouv.fr/schemas/cnigfr/sites-economiques-etablissement/latest/schema.json",
            "schema_type": "tableschema",
            "contact": "cnig@cnig.fr",
            "examples": [
                {
                    "title": "Exemple valide",
                    "name": "exemple-valide-csv",
                    "path": "https://github.com/cnigfr/schema-sites-economiques/schema/etablissement/raw/v1.0.0/exemple-valide.csv"
                }
            ],
            "labels": [
                "CNIG"
            ],
            "consolidation_dataset_id": null,
            "versions": [
                {
                    "version_name": "1.0.0",
                    "schema_url": "https://schema.data.gouv.fr/schemas/cnigfr/sites-economiques-etablissement/1.0.0/schema.json"
                }
            ],
            "external_doc": null,
            "external_tool": null,
            "homepage": "https://github.com/cnigfr/schema-sites-economiques.git",
            "datapackage_title": "Site Economique",
            "datapackage_name": "cnigfr/schema-sites-economiques",
            "datapackage_description": "Data package contenant 4 sch\u00e9mas : pole-eco, site-eco, terrain-eco, etablissement"
        },
        {
            "name": "CEREMA/schema-aire-livraison",
            "title": "Aires de livraison",
            "description": "Sp\u00e9cification du fichier d'\u00e9change relatif aux aires de livraison",
            "schema_url": "https://schema.data.gouv.fr/schemas/CEREMA/schema-aire-livraison/latest/schema.json",
            "schema_type": "tableschema",
            "contact": "mathieu.rajerison@cerema.fr",
            "examples": [
                {
                    "title": "Exemple valide pour Antibes",
                    "name": "exemple-antibes-csv",
                    "path": "https://raw.githubusercontent.com/CEREMA/schema-aire-livraison/v0.1.0/exemple-antibes.csv"
                }
            ],
            "labels": [],
            "consolidation_dataset_id": null,
            "versions": [
                {
                    "version_name": "0.1.0",
                    "schema_url": "https://schema.data.gouv.fr/schemas/CEREMA/schema-aire-livraison/0.1.0/schema.json"
                }
            ],
            "external_doc": null,
            "external_tool": null,
            "homepage": "https://github.com/CEREMA/schema-aire-livraison.git"
        }
    ]
}